{
 "blocks": {
  "languageVersion": 0,
  "blocks": [
   {
    "type": "Sc_Comment",
    "id": "_*@F5kqRv7XSliwAE!HA",
    "x": -883,
    "y": -795,
    "fields": {
     "COMMENT": "Harmonic zither (Jmcc) #11 ; Mouse control"
    },
    "next": {
     "block": {
      "type": "variables_set",
      "id": "elfha,73|G,=bhsZTWoe",
      "fields": {
       "VAR": {
        "id": "-$^#66L}S@0dn:unpGKt"
       }
      },
      "inputs": {
       "VALUE": {
        "block": {
         "type": "lists_create_with",
         "id": "Osx01m%[Vw1.pFk;0Pya",
         "inline": true,
         "extraState": {
          "itemCount": 12
         },
         "inputs": {
          "ADD0": {
           "block": {
            "type": "math_number",
            "id": "cMCF96Eo?4$Si{k%Bswc",
            "fields": {
             "NUM": 50
            }
           }
          },
          "ADD1": {
           "block": {
            "type": "math_number",
            "id": "jc;S8Gf5{xqj!!HUhyc:",
            "fields": {
             "NUM": 53.86
            }
           }
          },
          "ADD2": {
           "block": {
            "type": "math_number",
            "id": "I#{]!CL8moGpOw_t!1vx",
            "fields": {
             "NUM": 57.02
            }
           }
          },
          "ADD3": {
           "block": {
            "type": "math_number",
            "id": "Ps-|-QwX0hDo4,1*wgJY",
            "fields": {
             "NUM": 59.69
            }
           }
          },
          "ADD4": {
           "block": {
            "type": "math_number",
            "id": "[a5z^++ED#A?ZS`X3@wo",
            "fields": {
             "NUM": 62
            }
           }
          },
          "ADD5": {
           "block": {
            "type": "math_number",
            "id": "1q3n/umas3GR9/Vu5iV#",
            "fields": {
             "NUM": 64.04
            }
           }
          },
          "ADD6": {
           "block": {
            "type": "math_number",
            "id": "GsVx;8v59txJ5@e2C2Ff",
            "fields": {
             "NUM": 65.86
            }
           }
          },
          "ADD7": {
           "block": {
            "type": "math_number",
            "id": "Ez!W_oF-IPM/pjzjaT.m",
            "fields": {
             "NUM": 67.51
            }
           }
          },
          "ADD8": {
           "block": {
            "type": "math_number",
            "id": "EO3@!a?s[c/?~.5Nk8Ib",
            "fields": {
             "NUM": 69.02
            }
           }
          },
          "ADD9": {
           "block": {
            "type": "math_number",
            "id": "NZlxI(JNeh(b31/jTzfK",
            "fields": {
             "NUM": 71.69
            }
           }
          },
          "ADD10": {
           "block": {
            "type": "math_number",
            "id": "rm-{3,wlDdtUEC+MH$Z!",
            "fields": {
             "NUM": 72.88
            }
           }
          },
          "ADD11": {
           "block": {
            "type": "math_number",
            "id": "]QnF?r6+:qTvzaUxBqDA",
            "fields": {
             "NUM": 74
            }
           }
          }
         }
        }
       }
      },
      "next": {
       "block": {
        "type": "variables_set",
        "id": "e02$[r};S/GokrI4./Pr",
        "fields": {
         "VAR": {
          "id": "UIe[+g:my~IRuW7FaXx-"
         }
        },
        "inputs": {
         "VALUE": {
          "block": {
           "type": "Sc_BinaryOp",
           "id": "q1lavCxo]F*+M34.%jgy",
           "inline": true,
           "fields": {
            "OP": "/"
           },
           "inputs": {
            "LHS": {
             "block": {
              "type": "math_number",
              "id": "aac.VX@oe7+4R!ny{,Js",
              "fields": {
               "NUM": 0.5
              }
             }
            },
            "RHS": {
             "block": {
              "type": "Sc_BinaryOp",
              "id": "e.F:9YY%z,;.Tsperb$)",
              "inline": true,
              "fields": {
               "OP": "-"
              },
              "inputs": {
               "LHS": {
                "block": {
                 "type": "Sc_ArrayProc1",
                 "id": "trGu?y?DT_x)kAK#Pk1i",
                 "fields": {
                  "OP": "size"
                 },
                 "inputs": {
                  "IN": {
                   "block": {
                    "type": "variables_get",
                    "id": ")^mp^@Rs$GXFh%qd{1r8",
                    "fields": {
                     "VAR": {
                      "id": "-$^#66L}S@0dn:unpGKt"
                     }
                    }
                   }
                  }
                 }
                }
               },
               "RHS": {
                "block": {
                 "type": "math_number",
                 "id": "qV]zaVom,r1gp/RXN75y",
                 "fields": {
                  "NUM": 1
                 }
                }
               }
              }
             }
            }
           }
          }
         }
        },
        "next": {
         "block": {
          "type": "variables_set",
          "id": ":N=1,,fy[[a8$yyn)IDK",
          "fields": {
           "VAR": {
            "id": ".};}eh:S)IhEi*^hpFDP"
           }
          },
          "inputs": {
           "VALUE": {
            "block": {
             "type": "Sc_BinaryOp",
             "id": "4HFbn@42X[{R.)+VUNq_",
             "inline": true,
             "fields": {
              "OP": "/"
             },
             "inputs": {
              "LHS": {
               "block": {
                "type": "math_number",
                "id": ")M?2!{1j22ZZ7c_D=d#S",
                "fields": {
                 "NUM": 1.5
                }
               }
              },
              "RHS": {
               "block": {
                "type": "Sc_BinaryOp",
                "id": "3RhvPms`L+.XW*J9j1#2",
                "inline": true,
                "fields": {
                 "OP": "-"
                },
                "inputs": {
                 "LHS": {
                  "block": {
                   "type": "Sc_ArrayProc1",
                   "id": "EQLrV!AbV(([HW:,6pfJ",
                   "fields": {
                    "OP": "size"
                   },
                   "inputs": {
                    "IN": {
                     "block": {
                      "type": "variables_get",
                      "id": "/2Y,tGrU~v)Mfysy=xa%",
                      "fields": {
                       "VAR": {
                        "id": "-$^#66L}S@0dn:unpGKt"
                       }
                      }
                     }
                    }
                   }
                  }
                 },
                 "RHS": {
                  "block": {
                   "type": "math_number",
                   "id": "|QsiBR}hB@nVr6XAmvJO",
                   "fields": {
                    "NUM": 1
                   }
                  }
                 }
                }
               }
              }
             }
            }
           }
          },
          "next": {
           "block": {
            "type": "variables_set",
            "id": "O.rdRldK[0B*86SnaQ?7",
            "fields": {
             "VAR": {
              "id": "|Ut%#L4s^tP_K_v.;lfe"
             }
            },
            "inputs": {
             "VALUE": {
              "block": {
               "type": "Sc_Proc1",
               "id": "04fGnv^,[pTW8Y2oV-g?",
               "inputs": {
                "VAR": {
                 "block": {
                  "type": "variables_get",
                  "id": "R(K=%Ws2Ff4.QNJiTglz",
                  "fields": {
                   "VAR": {
                    "id": "iPapFXOw2jd`=nC|z.CN"
                   }
                  }
                 }
                },
                "RETURN": {
                 "block": {
                  "type": "Sc_EqPan2",
                  "id": "1ScH=b)_9CN00obsz_cx",
                  "inputs": {
                   "IN": {
                    "block": {
                     "type": "Sc_CombL",
                     "id": "uorfE9S=+Kq)mZb++~BK",
                     "inputs": {
                      "IN": {
                       "block": {
                        "type": "Sc_PinkNoise",
                        "id": ":bH0o,.):DHPW~qHLP%%",
                        "inline": false,
                        "inputs": {
                         "MUL": {
                          "shadow": {
                           "type": "math_number",
                           "id": "=GW):l$gV%U1SBmy5XxM",
                           "fields": {
                            "NUM": 1
                           }
                          },
                          "block": {
                           "type": "Sc_Decay",
                           "id": "4UMFvuev5N}{E^,ngs54",
                           "inputs": {
                            "IN": {
                             "block": {
                              "type": "Sc_UnaryOp",
                              "id": "[Wcb{[)GMRRBb=G9Tw*(",
                              "fields": {
                               "OP": "Abs"
                              },
                              "inputs": {
                               "IN": {
                                "block": {
                                 "type": "Sc_HPZ1",
                                 "id": ")*Wb;gepYCOad6ic~_OH",
                                 "inputs": {
                                  "IN": {
                                   "block": {
                                    "type": "Sc_BinaryOp",
                                    "id": "]Zvp)^u^[Vur3sNnY;hi",
                                    "inline": true,
                                    "fields": {
                                     "OP": ">"
                                    },
                                    "inputs": {
                                     "LHS": {
                                      "block": {
                                       "type": "Sc_MouseX",
                                       "id": "JRGD(gt52IsjJa+@Frhh",
                                       "inline": true,
                                       "inputs": {
                                        "MINVAL": {
                                         "block": {
                                          "type": "math_number",
                                          "id": "$t,=Lx_?TUaDOOz(vjG.",
                                          "fields": {
                                           "NUM": 0
                                          }
                                         }
                                        },
                                        "MAXVAL": {
                                         "block": {
                                          "type": "math_number",
                                          "id": "7oM0v+e=aur8FP}D@QX+",
                                          "fields": {
                                           "NUM": 1
                                          }
                                         }
                                        },
                                        "WARP": {
                                         "block": {
                                          "type": "math_number",
                                          "id": "(Zwe$Y^TN)Iw,39/w`W-",
                                          "fields": {
                                           "NUM": 0
                                          }
                                         }
                                        },
                                        "LAG": {
                                         "block": {
                                          "type": "math_number",
                                          "id": "fx0^i{o*l*`ZGIl/il{F",
                                          "fields": {
                                           "NUM": 0.2
                                          }
                                         }
                                        },
                                        "MUL": {
                                         "shadow": {
                                          "type": "math_number",
                                          "id": "GKQs0^~OeH}2wF1i-|$@",
                                          "fields": {
                                           "NUM": 1
                                          }
                                         }
                                        },
                                        "ADD": {
                                         "shadow": {
                                          "type": "math_number",
                                          "id": "*t9K+vRg69Qp}6u:Pure",
                                          "fields": {
                                           "NUM": 0
                                          }
                                         }
                                        }
                                       }
                                      }
                                     },
                                     "RHS": {
                                      "block": {
                                       "type": "Sc_BinaryOp",
                                       "id": "nC7WP=z33v~GXz2oJ%-w",
                                       "inline": true,
                                       "fields": {
                                        "OP": "*"
                                       },
                                       "inputs": {
                                        "LHS": {
                                         "block": {
                                          "type": "Sc_BinaryOp",
                                          "id": "IToHFBs(c0a:W]CXOKJ]",
                                          "inline": true,
                                          "fields": {
                                           "OP": "+"
                                          },
                                          "inputs": {
                                           "LHS": {
                                            "block": {
                                             "type": "math_number",
                                             "id": "As=:x55qIrG$?,wC8:4|",
                                             "fields": {
                                              "NUM": 0.25
                                             }
                                            }
                                           },
                                           "RHS": {
                                            "block": {
                                             "type": "variables_get",
                                             "id": "dy3BJk;,*-J~f8z$T[dr",
                                             "fields": {
                                              "VAR": {
                                               "id": "iPapFXOw2jd`=nC|z.CN"
                                              }
                                             }
                                            }
                                           }
                                          }
                                         }
                                        },
                                        "RHS": {
                                         "block": {
                                          "type": "variables_get",
                                          "id": "R|kU%EK7gLTz?Ze+8ORc",
                                          "fields": {
                                           "VAR": {
                                            "id": "UIe[+g:my~IRuW7FaXx-"
                                           }
                                          }
                                         }
                                        }
                                       }
                                      }
                                     }
                                    }
                                   }
                                  },
                                  "MUL": {
                                   "shadow": {
                                    "type": "math_number",
                                    "id": "k;bP4VF%482sU!~QfEsP",
                                    "fields": {
                                     "NUM": 1
                                    }
                                   }
                                  },
                                  "ADD": {
                                   "shadow": {
                                    "type": "math_number",
                                    "id": "rnL^BEY#{*P0DQ`={x[O",
                                    "fields": {
                                     "NUM": 0
                                    }
                                   }
                                  }
                                 }
                                }
                               }
                              }
                             }
                            },
                            "DECAYTIME": {
                             "block": {
                              "type": "math_number",
                              "id": "^5Ag7;2$z2h##|RqzZV{",
                              "fields": {
                               "NUM": 0.05
                              }
                             }
                            },
                            "MUL": {
                             "shadow": {
                              "type": "math_number",
                              "id": "@TNu1DUwG4w1=Vj#g!EL",
                              "fields": {
                               "NUM": 1
                              }
                             }
                            },
                            "ADD": {
                             "shadow": {
                              "type": "math_number",
                              "id": "vQ`EIl.U4`~~v8.lua2G",
                              "fields": {
                               "NUM": 0
                              }
                             }
                            }
                           }
                          }
                         },
                         "ADD": {
                          "shadow": {
                           "type": "math_number",
                           "id": "20!X$X3t98Xt,zAq7mC$",
                           "fields": {
                            "NUM": 0
                           }
                          }
                         }
                        }
                       }
                      },
                      "MAXDELAYTIME": {
                       "block": {
                        "type": "Sc_UnaryOp",
                        "id": "Ft9dVF98B=N_.Y]I-;BL",
                        "fields": {
                         "OP": "Recip"
                        },
                        "inputs": {
                         "IN": {
                          "block": {
                           "type": "Sc_UnaryOp",
                           "id": "EzBQ)o_A?*GlM)}aiO!r",
                           "fields": {
                            "OP": "MidiCps"
                           },
                           "inputs": {
                            "IN": {
                             "block": {
                              "type": "Sc_ArrayProc2",
                              "id": "8:M=-@Ng_c(6xYa=@#]h",
                              "inline": true,
                              "fields": {
                               "OP": "at"
                              },
                              "inputs": {
                               "LHS": {
                                "block": {
                                 "type": "variables_get",
                                 "id": "PV(vn.fQmKXXBYywB^:k",
                                 "fields": {
                                  "VAR": {
                                   "id": "-$^#66L}S@0dn:unpGKt"
                                  }
                                 }
                                }
                               },
                               "RHS": {
                                "block": {
                                 "type": "variables_get",
                                 "id": "~:5c1GR9TNnzj`|EH!zc",
                                 "fields": {
                                  "VAR": {
                                   "id": "iPapFXOw2jd`=nC|z.CN"
                                  }
                                 }
                                }
                               }
                              }
                             }
                            }
                           }
                          }
                         }
                        }
                       }
                      },
                      "DELAYTIME": {
                       "block": {
                        "type": "Sc_UnaryOp",
                        "id": "]FOBZv-Y=Ff=XwaRD6K$",
                        "fields": {
                         "OP": "Recip"
                        },
                        "inputs": {
                         "IN": {
                          "block": {
                           "type": "Sc_UnaryOp",
                           "id": "$`0v+?-SH?ISx.~~?60v",
                           "fields": {
                            "OP": "MidiCps"
                           },
                           "inputs": {
                            "IN": {
                             "block": {
                              "type": "Sc_ArrayProc2",
                              "id": "8-j,6Z9PA2[6JNox2rS@",
                              "inline": true,
                              "fields": {
                               "OP": "at"
                              },
                              "inputs": {
                               "LHS": {
                                "block": {
                                 "type": "variables_get",
                                 "id": "c23pM%mxpB%6~ybv*Ry5",
                                 "fields": {
                                  "VAR": {
                                   "id": "-$^#66L}S@0dn:unpGKt"
                                  }
                                 }
                                }
                               },
                               "RHS": {
                                "block": {
                                 "type": "variables_get",
                                 "id": "V8`md5DU3].^_{lx)yb`",
                                 "fields": {
                                  "VAR": {
                                   "id": "iPapFXOw2jd`=nC|z.CN"
                                  }
                                 }
                                }
                               }
                              }
                             }
                            }
                           }
                          }
                         }
                        }
                       }
                      },
                      "DECAYTIME": {
                       "block": {
                        "type": "math_number",
                        "id": "=pzvSOlsK{BNS1m98$aj",
                        "fields": {
                         "NUM": 8
                        }
                       }
                      },
                      "MUL": {
                       "shadow": {
                        "type": "math_number",
                        "id": "|,72`O/z|WcP](bmq/{,",
                        "fields": {
                         "NUM": 1
                        }
                       }
                      },
                      "ADD": {
                       "shadow": {
                        "type": "math_number",
                        "id": "~kQtrd]{Zb-wnaW.61(l",
                        "fields": {
                         "NUM": 0
                        }
                       }
                      }
                     }
                    }
                   },
                   "POS": {
                    "block": {
                     "type": "Sc_BinaryOp",
                     "id": "?$3UdnV,.hBcE?OZd!8?",
                     "inline": true,
                     "fields": {
                      "OP": "-"
                     },
                     "inputs": {
                      "LHS": {
                       "block": {
                        "type": "Sc_BinaryOp",
                        "id": "o}Ta~+ScAA]|(7_5^q9^",
                        "inline": true,
                        "fields": {
                         "OP": "*"
                        },
                        "inputs": {
                         "LHS": {
                          "block": {
                           "type": "Sc_BinaryOp",
                           "id": "aJF8Q!=9KsMKUY(Wta4a",
                           "inline": true,
                           "fields": {
                            "OP": "-"
                           },
                           "inputs": {
                            "LHS": {
                             "block": {
                              "type": "variables_get",
                              "id": "huU![GL1n*1h-cGGX?RX",
                              "fields": {
                               "VAR": {
                                "id": "iPapFXOw2jd`=nC|z.CN"
                               }
                              }
                             }
                            },
                            "RHS": {
                             "block": {
                              "type": "math_number",
                              "id": "{0{C|=9nyLhz1xsD[6r5",
                              "fields": {
                               "NUM": 1
                              }
                             }
                            }
                           }
                          }
                         },
                         "RHS": {
                          "block": {
                           "type": "variables_get",
                           "id": "D:7|~7KI5dA{+2(~Ar4V",
                           "fields": {
                            "VAR": {
                             "id": ".};}eh:S)IhEi*^hpFDP"
                            }
                           }
                          }
                         }
                        }
                       }
                      },
                      "RHS": {
                       "block": {
                        "type": "math_number",
                        "id": "[YnfM/%IVWDVV_9_)%2+",
                        "fields": {
                         "NUM": 0.75
                        }
                       }
                      }
                     }
                    }
                   },
                   "MUL": {
                    "shadow": {
                     "type": "math_number",
                     "id": "rR*CC1DxLtd}4=tQ93dh",
                     "fields": {
                      "NUM": 1
                     }
                    }
                   },
                   "ADD": {
                    "shadow": {
                     "type": "math_number",
                     "id": "uK~4Ed(}_lF4Jz;T:ap7",
                     "fields": {
                      "NUM": 0
                     }
                    }
                   }
                  }
                 }
                }
               }
              }
             }
            },
            "next": {
             "block": {
              "type": "Sc_Play",
              "id": "*^F0]?xl6].__WsR|FXc",
              "inputs": {
               "CODE": {
                "block": {
                 "type": "Sc_LeakDC",
                 "id": "j6SvLoi(K^6vWXQQh@!%",
                 "inline": true,
                 "inputs": {
                  "IN": {
                   "block": {
                    "type": "Sc_LPF",
                    "id": "a~;u2nI,BW!(ofPG`F:m",
                    "inline": true,
                    "inputs": {
                     "IN": {
                      "block": {
                       "type": "Sc_ArrayProc1",
                       "id": "hYLv]]t2pek?WAg|sE!0",
                       "fields": {
                        "OP": "sum"
                       },
                       "inputs": {
                        "IN": {
                         "block": {
                          "type": "Sc_ArrayCollect",
                          "id": "Z+|R;}ZheVyE=uV)5]K-",
                          "inline": true,
                          "inputs": {
                           "ARRAY": {
                            "block": {
                             "type": "Sc_ArrayFromTo",
                             "id": "fw:fvfk]|)ink;zRE|Pv",
                             "inline": true,
                             "inputs": {
                              "FROM": {
                               "block": {
                                "type": "math_number",
                                "id": "@zwfJ=daWI]Ot={xKu;)",
                                "fields": {
                                 "NUM": 1
                                }
                               }
                              },
                              "TO": {
                               "block": {
                                "type": "Sc_ArrayProc1",
                                "id": "xWaPbUil+6KxZzRe{sAA",
                                "fields": {
                                 "OP": "size"
                                },
                                "inputs": {
                                 "IN": {
                                  "block": {
                                   "type": "variables_get",
                                   "id": "J=yNTGr^oqrFdz`*)0_e",
                                   "fields": {
                                    "VAR": {
                                     "id": "-$^#66L}S@0dn:unpGKt"
                                    }
                                   }
                                  }
                                 }
                                }
                               }
                              }
                             }
                            }
                           },
                           "PROC": {
                            "block": {
                             "type": "variables_get",
                             "id": "HlJ2(rsfa@3hJ^9RWLC~",
                             "fields": {
                              "VAR": {
                               "id": "|Ut%#L4s^tP_K_v.;lfe"
                              }
                             }
                            }
                           }
                          }
                         }
                        }
                       }
                      }
                     },
                     "FREQ": {
                      "block": {
                       "type": "math_number",
                       "id": "A2VIgbtbxAck0~)uu3N.",
                       "fields": {
                        "NUM": 12000
                       }
                      }
                     },
                     "MUL": {
                      "shadow": {
                       "type": "math_number",
                       "id": "6%:RUe$XSsBIVceY-n@f",
                       "fields": {
                        "NUM": 1
                       }
                      }
                     },
                     "ADD": {
                      "shadow": {
                       "type": "math_number",
                       "id": "D/kLJrP9mRT1G+P5w:[=",
                       "fields": {
                        "NUM": 0
                       }
                      }
                     }
                    }
                   }
                  },
                  "COEF": {
                   "block": {
                    "type": "math_number",
                    "id": "030WQIZz)5JHkw(E_ORF",
                    "fields": {
                     "NUM": 0.995
                    }
                   }
                  },
                  "MUL": {
                   "shadow": {
                    "type": "math_number",
                    "id": "Aj)N8%#hK,b{rgQC;nRT",
                    "fields": {
                     "NUM": 1
                    }
                   }
                  },
                  "ADD": {
                   "shadow": {
                    "type": "math_number",
                    "id": "u12ec]3~#Xkl`M3^-JkX",
                    "fields": {
                     "NUM": 0
                    }
                   }
                  }
                 }
                }
               }
              }
             }
            }
           }
          }
         }
        }
       }
      }
     }
    }
   }
  ]
 },
 "variables": [
  {
   "name": "pitch",
   "id": "-$^#66L}S@0dn:unpGKt"
  },
  {
   "name": "triggerSpacing",
   "id": "UIe[+g:my~IRuW7FaXx-"
  },
  {
   "name": "panSpacing",
   "id": ".};}eh:S)IhEi*^hpFDP"
  },
  {
   "name": "stringFunc",
   "id": "|Ut%#L4s^tP_K_v.;lfe"
  },
  {
   "name": "i",
   "id": "iPapFXOw2jd`=nC|z.CN"
  }
 ]
}
