{
 "blocks": {
  "languageVersion": 0,
  "blocks": [
   {
    "type": "Sc_Comment",
    "id": "t5W6bjuV[ZWE)ccAm9ir",
    "x": 0,
    "y": 0,
    "fields": {
     "COMMENT": "Generative landscape (Jr)"
    },
    "next": {
     "block": {
      "type": "variables_set",
      "id": "=;laRo)c1F5;!L.ImUZ%",
      "fields": {
       "VAR": {
        "id": "ft8wODt6uo)_f/Dl#?(G"
       }
      },
      "inputs": {
       "VALUE": {
        "block": {
         "type": "Sc_MouseX",
         "id": "sheDNq8oOIt)p=fw%=r;",
         "inline": true,
         "inputs": {
          "MINVAL": {
           "block": {
            "type": "math_number",
            "id": "u9Uq-y{,%~ZD!0VXw.(6",
            "fields": {
             "NUM": -10
            }
           }
          },
          "MAXVAL": {
           "block": {
            "type": "math_number",
            "id": ",aoJyg^1*xns{q!sib1?",
            "fields": {
             "NUM": 10
            }
           }
          },
          "WARP": {
           "block": {
            "type": "math_number",
            "id": "An(q%A?eD9lu~@[LzuBR",
            "fields": {
             "NUM": 0
            }
           }
          },
          "LAG": {
           "block": {
            "type": "math_number",
            "id": "-4k%K`5K#.}NMHF1zm#Q",
            "fields": {
             "NUM": 0.1
            }
           }
          },
          "MUL": {
           "shadow": {
            "type": "math_number",
            "id": "(;7V(U3-agu2n.9/~amH",
            "fields": {
             "NUM": 1
            }
           }
          },
          "ADD": {
           "shadow": {
            "type": "math_number",
            "id": "j1_{I|9_5G$t^Zq7J69p",
            "fields": {
             "NUM": 0
            }
           }
          }
         }
        }
       }
      },
      "next": {
       "block": {
        "type": "variables_set",
        "id": "Bv!PR*ByAVK6wfF]RJ!Y",
        "fields": {
         "VAR": {
          "id": "R$HXOP(9X.:kG=s+dhzt"
         }
        },
        "inputs": {
         "VALUE": {
          "block": {
           "type": "Sc_MouseY",
           "id": "ZT3rZE%jW4V44ibX`N]7",
           "inline": true,
           "inputs": {
            "MINVAL": {
             "block": {
              "type": "math_number",
              "id": "2T]Kc#E)j[n#h!ZmejOu",
              "fields": {
               "NUM": 0
              }
             }
            },
            "MAXVAL": {
             "block": {
              "type": "math_number",
              "id": "f65l$UT*nRAGn8k3j?;E",
              "fields": {
               "NUM": 5
              }
             }
            },
            "WARP": {
             "block": {
              "type": "math_number",
              "id": "T6~[1[`JLSlfS|Z!XJWM",
              "fields": {
               "NUM": 0
              }
             }
            },
            "LAG": {
             "block": {
              "type": "math_number",
              "id": "s[X$uNuAFoLjE}2I3{Vt",
              "fields": {
               "NUM": 0.1
              }
             }
            },
            "MUL": {
             "shadow": {
              "type": "math_number",
              "id": "-`(sVR6RYwS}!];edi8!",
              "fields": {
               "NUM": 1
              }
             }
            },
            "ADD": {
             "shadow": {
              "type": "math_number",
              "id": "nqJK#MH}1#*pDKtW4PN%",
              "fields": {
               "NUM": 0
              }
             }
            }
           }
          }
         }
        },
        "next": {
         "block": {
          "type": "variables_set",
          "id": "T{`7y`X`a}1a?~03,W@g",
          "fields": {
           "VAR": {
            "id": "xZLz3r*Z0?fDdj!]P5=["
           }
          },
          "inputs": {
           "VALUE": {
            "block": {
             "type": "Sc_BinaryOp",
             "id": "_N3,xl!1mx1-A/u|;8Vf",
             "inline": true,
             "fields": {
              "OP": "+"
             },
             "inputs": {
              "LHS": {
               "block": {
                "type": "Sc_BinaryOp",
                "id": "-@;ec%BdX@T@UmQ(*JFD",
                "inline": true,
                "fields": {
                 "OP": "*"
                },
                "inputs": {
                 "LHS": {
                  "block": {
                   "type": "Sc_LFSaw",
                   "id": "M}?^l62}9dd|TYD~xW%c",
                   "inline": true,
                   "inputs": {
                    "FREQ": {
                     "block": {
                      "type": "math_number",
                      "id": "IShBNE-~:munz9C)ah@H",
                      "fields": {
                       "NUM": 0.062
                      }
                     }
                    },
                    "IPHASE": {
                     "block": {
                      "type": "math_number",
                      "id": "3}u}l!09;*8;FUVhxxV1",
                      "fields": {
                       "NUM": 0
                      }
                     }
                    },
                    "MUL": {
                     "shadow": {
                      "type": "math_number",
                      "id": "oo5T{+QJ:Y`bkXO@-G{e",
                      "fields": {
                       "NUM": 1
                      }
                     }
                    },
                    "ADD": {
                     "shadow": {
                      "type": "math_number",
                      "id": "$UvHXT#=0K:B/L[Zwf0[",
                      "fields": {
                       "NUM": 0
                      }
                     }
                    }
                   }
                  }
                 },
                 "RHS": {
                  "block": {
                   "type": "math_number",
                   "id": "iY[EN(+aI(!}?D90QRw/",
                   "fields": {
                    "NUM": 10
                   }
                  }
                 }
                }
               }
              },
              "RHS": {
               "block": {
                "type": "Sc_BinaryOp",
                "id": "7dT.=Td38SLPF8N!Pc#R",
                "inline": true,
                "fields": {
                 "OP": "*"
                },
                "inputs": {
                 "LHS": {
                  "block": {
                   "type": "variables_get",
                   "id": "@jSY(Hd7^wc6IeRz7_m$",
                   "fields": {
                    "VAR": {
                     "id": "R$HXOP(9X.:kG=s+dhzt"
                    }
                   }
                  }
                 },
                 "RHS": {
                  "block": {
                   "type": "Sc_UnaryOp",
                   "id": "[b3#`SFn/;%A[sW9!*0I",
                   "fields": {
                    "OP": "Abs"
                   },
                   "inputs": {
                    "IN": {
                     "block": {
                      "type": "Sc_ArrayFromTo",
                      "id": "Orgye(3,ZLV,x^^tgx(]",
                      "inline": true,
                      "inputs": {
                       "FROM": {
                        "block": {
                         "type": "math_number",
                         "id": "#w~SCUAk:5j,V{D^Z-UJ",
                         "fields": {
                          "NUM": 0
                         }
                        }
                       },
                       "TO": {
                        "block": {
                         "type": "math_number",
                         "id": "C(ZGRFmb[_:3;he}!A3K",
                         "fields": {
                          "NUM": 8
                         }
                        }
                       }
                      }
                     }
                    }
                   }
                  }
                 }
                }
               }
              }
             }
            }
           }
          },
          "next": {
           "block": {
            "type": "variables_set",
            "id": "X,PODyg;9Uz4_oCFXz@C",
            "fields": {
             "VAR": {
              "id": "6=p[(Vi!RJ=~tGwys3XS"
             }
            },
            "inputs": {
             "VALUE": {
              "block": {
               "type": "Sc_UnaryOp",
               "id": "j$9#![|2jP^Z@onyHdZF",
               "fields": {
                "OP": "Frac"
               },
               "inputs": {
                "IN": {
                 "block": {
                  "type": "variables_get",
                  "id": "fLz|q:HZ7b2kW]W}iCPT",
                  "fields": {
                   "VAR": {
                    "id": "xZLz3r*Z0?fDdj!]P5=["
                   }
                  }
                 }
                }
               }
              }
             }
            },
            "next": {
             "block": {
              "type": "variables_set",
              "id": "_jZ-FZV60q]lPVcIyKx:",
              "fields": {
               "VAR": {
                "id": "WWbfq-1I)$$#l.vtB(72"
               }
              },
              "inputs": {
               "VALUE": {
                "block": {
                 "type": "Sc_BinaryOp",
                 "id": "nb2tO$kTA(.)OEbG5mv/",
                 "inline": true,
                 "fields": {
                  "OP": "+"
                 },
                 "inputs": {
                  "LHS": {
                   "block": {
                    "type": "Sc_UnaryOp",
                    "id": "2IoB1oR0p`RhM[dxYLL[",
                    "fields": {
                     "OP": "Neg"
                    },
                    "inputs": {
                     "IN": {
                      "block": {
                       "type": "Sc_ModDif",
                       "id": "sb}U-%6yUkGff*~D8hZ?",
                       "inline": true,
                       "inputs": {
                        "X": {
                         "block": {
                          "type": "variables_get",
                          "id": "Rz!8GGfr(6koTvl~coNm",
                          "fields": {
                           "VAR": {
                            "id": "6=p[(Vi!RJ=~tGwys3XS"
                           }
                          }
                         }
                        },
                        "Y": {
                         "block": {
                          "type": "math_number",
                          "id": "9aPOtMmk+vnUh%9QCWs!",
                          "fields": {
                           "NUM": 0.5
                          }
                         }
                        },
                        "MOD": {
                         "block": {
                          "type": "math_number",
                          "id": "yr}NF[s|T76d{q1XRO?9",
                          "fields": {
                           "NUM": 1
                          }
                         }
                        },
                        "MUL": {
                         "block": {
                          "type": "math_number",
                          "id": "t;ac0l$e0X7QqLbSQmz?",
                          "fields": {
                           "NUM": 1
                          }
                         }
                        },
                        "ADD": {
                         "block": {
                          "type": "math_number",
                          "id": "q1H-wO`21_}!BWpX_*/q",
                          "fields": {
                           "NUM": 0
                          }
                         }
                        }
                       }
                      }
                     }
                    }
                   }
                  },
                  "RHS": {
                   "block": {
                    "type": "math_number",
                    "id": "sbr7ZY9#^lq-W#2n]?cl",
                    "fields": {
                     "NUM": 0.8
                    }
                   }
                  }
                 }
                }
               }
              },
              "next": {
               "block": {
                "type": "variables_set",
                "id": "Rw$rP.raET[y?}c$GBMy",
                "fields": {
                 "VAR": {
                  "id": "UQ5_RVY~(jTNVvJ@sY#U"
                 }
                },
                "inputs": {
                 "VALUE": {
                  "block": {
                   "type": "Sc_BinaryOp",
                   "id": "X/Y49?R2fBf:2ol%#2Ox",
                   "inline": true,
                   "fields": {
                    "OP": "+"
                   },
                   "inputs": {
                    "LHS": {
                     "block": {
                      "type": "Sc_BinaryOp",
                      "id": "FytqLo8I|rW;lTeezw)%",
                      "inline": true,
                      "fields": {
                       "OP": "Gcd"
                      },
                      "inputs": {
                       "LHS": {
                        "block": {
                         "type": "variables_get",
                         "id": "|@IGsq:_ZeCGg![]Jh?[",
                         "fields": {
                          "VAR": {
                           "id": "xZLz3r*Z0?fDdj!]P5=["
                          }
                         }
                        }
                       },
                       "RHS": {
                        "block": {
                         "type": "variables_get",
                         "id": "8Hcsi`F+GAp%gJT`#w?K",
                         "fields": {
                          "VAR": {
                           "id": "ft8wODt6uo)_f/Dl#?(G"
                          }
                         }
                        }
                       }
                      }
                     }
                    },
                    "RHS": {
                     "block": {
                      "type": "variables_get",
                      "id": "N0QKxF=H*u$HvPnwgnkt",
                      "fields": {
                       "VAR": {
                        "id": "6=p[(Vi!RJ=~tGwys3XS"
                       }
                      }
                     }
                    }
                   }
                  }
                 }
                },
                "next": {
                 "block": {
                  "type": "variables_set",
                  "id": "E?P|CCzJ06pDqT}jZWut",
                  "fields": {
                   "VAR": {
                    "id": "x~3U?9rn;:L#]M/uSTy_"
                   }
                  },
                  "inputs": {
                   "VALUE": {
                    "block": {
                     "type": "Sc_BinaryOp",
                     "id": "*gev(ZT-{o^s^Kv+!_Hx",
                     "inline": true,
                     "fields": {
                      "OP": "+"
                     },
                     "inputs": {
                      "LHS": {
                       "block": {
                        "type": "Sc_BinaryOp",
                        "id": "%c`KmuVH2ckG_-Bd4YW0",
                        "inline": true,
                        "fields": {
                         "OP": "Lcm"
                        },
                        "inputs": {
                         "LHS": {
                          "block": {
                           "type": "variables_get",
                           "id": "rfvVH?LVC`?GAaoL|2Rn",
                           "fields": {
                            "VAR": {
                             "id": "xZLz3r*Z0?fDdj!]P5=["
                            }
                           }
                          }
                         },
                         "RHS": {
                          "block": {
                           "type": "variables_get",
                           "id": "i4m)K2eJP#!Tpyh$h`*j",
                           "fields": {
                            "VAR": {
                             "id": "ft8wODt6uo)_f/Dl#?(G"
                            }
                           }
                          }
                         }
                        }
                       }
                      },
                      "RHS": {
                       "block": {
                        "type": "variables_get",
                        "id": "CpXI;|0ioO(Xam@S4Wkh",
                        "fields": {
                         "VAR": {
                          "id": "6=p[(Vi!RJ=~tGwys3XS"
                         }
                        }
                       }
                      }
                     }
                    }
                   }
                  },
                  "next": {
                   "block": {
                    "type": "variables_set",
                    "id": "o4kmhKJ7a1C*Xy#_l,pG",
                    "fields": {
                     "VAR": {
                      "id": "uTY9bqBm5*:wUjuQ(0@N"
                     }
                    },
                    "inputs": {
                     "VALUE": {
                      "block": {
                       "type": "Sc_BinaryOp",
                       "id": "xhsh--E,u/^UKdN1;Z9?",
                       "inline": true,
                       "fields": {
                        "OP": "*"
                       },
                       "inputs": {
                        "LHS": {
                         "block": {
                          "type": "Sc_BinaryOp",
                          "id": "`(eZJt=p)IVtb|8s.8sm",
                          "inline": true,
                          "fields": {
                           "OP": "+"
                          },
                          "inputs": {
                           "LHS": {
                            "block": {
                             "type": "Sc_UnaryOp",
                             "id": "#ur1qu7kAi}f09ywa=[$",
                             "fields": {
                              "OP": "Abs"
                             },
                             "inputs": {
                              "IN": {
                               "block": {
                                "type": "Sc_UnaryOp",
                                "id": "^~$Dn!OO4+3aSJdGdc^w",
                                "fields": {
                                 "OP": "Abs"
                                },
                                "inputs": {
                                 "IN": {
                                  "block": {
                                   "type": "lists_create_with",
                                   "id": "Em+n/d]33nK];QvSJWEL",
                                   "inline": true,
                                   "extraState": {
                                    "itemCount": 2
                                   },
                                   "inputs": {
                                    "ADD0": {
                                     "block": {
                                      "type": "variables_get",
                                      "id": "z3oB/0!C5k3g4Cp]}8+6",
                                      "fields": {
                                       "VAR": {
                                        "id": "UQ5_RVY~(jTNVvJ@sY#U"
                                       }
                                      }
                                     }
                                    },
                                    "ADD1": {
                                     "block": {
                                      "type": "variables_get",
                                      "id": "dH8}q+j#Mw+oPb!bkCOt",
                                      "fields": {
                                       "VAR": {
                                        "id": "x~3U?9rn;:L#]M/uSTy_"
                                       }
                                      }
                                     }
                                    }
                                   }
                                  }
                                 }
                                }
                               }
                              }
                             }
                            }
                           },
                           "RHS": {
                            "block": {
                             "type": "math_number",
                             "id": "`?Xso(]nn]=9fATeJiQK",
                             "fields": {
                              "NUM": 1
                             }
                            }
                           }
                          }
                         }
                        },
                        "RHS": {
                         "block": {
                          "type": "math_number",
                          "id": "7qn)4_Np[7vN}%g[G`]%",
                          "fields": {
                           "NUM": 120
                          }
                         }
                        }
                       }
                      }
                     }
                    },
                    "next": {
                     "block": {
                      "type": "variables_set",
                      "id": "BXVQSkJ01)iwT;,E%$]9",
                      "fields": {
                       "VAR": {
                        "id": "ewK2$,B*9$K-@m3*cnWs"
                       }
                      },
                      "inputs": {
                       "VALUE": {
                        "block": {
                         "type": "Sc_BinaryOp",
                         "id": "tElyk4%L~c0g[T7g57UB",
                         "inline": true,
                         "fields": {
                          "OP": "*"
                         },
                         "inputs": {
                          "LHS": {
                           "block": {
                            "type": "Sc_AmpComp",
                            "id": "z|PE)F]Rs]N3Rgz$iQ(h",
                            "inline": true,
                            "inputs": {
                             "FREQ": {
                              "block": {
                               "type": "variables_get",
                               "id": "K+h]J}k{(reE|Evsj?Rz",
                               "fields": {
                                "VAR": {
                                 "id": "uTY9bqBm5*:wUjuQ(0@N"
                                }
                               }
                              }
                             },
                             "ROOT": {
                              "block": {
                               "type": "math_number",
                               "id": "Ju(4:ChowNDqDox3|-En",
                               "fields": {
                                "NUM": 261.625
                               }
                              }
                             },
                             "EXP": {
                              "block": {
                               "type": "Sc_BinaryOp",
                               "id": "%LZ`4zh`xEv]w}D/*FU#",
                               "inline": true,
                               "fields": {
                                "OP": "/"
                               },
                               "inputs": {
                                "LHS": {
                                 "block": {
                                  "type": "math_number",
                                  "id": "}|D;.8tlGyaTa?d6|S53",
                                  "fields": {
                                   "NUM": 1
                                  }
                                 }
                                },
                                "RHS": {
                                 "block": {
                                  "type": "math_number",
                                  "id": "c{R:Ls7]^y(Qn~mXb(rd",
                                  "fields": {
                                   "NUM": 3
                                  }
                                 }
                                }
                               }
                              }
                             },
                             "MUL": {
                              "shadow": {
                               "type": "math_number",
                               "id": "t|*,fnOTAD~P1!W^-ytC",
                               "fields": {
                                "NUM": 1
                               }
                              }
                             },
                             "ADD": {
                              "shadow": {
                               "type": "math_number",
                               "id": ")-fJ/0m|Yx2`,hEEqb3u",
                               "fields": {
                                "NUM": 0
                               }
                              }
                             }
                            }
                           }
                          },
                          "RHS": {
                           "block": {
                            "type": "variables_get",
                            "id": ",KVYbBGq{P_}LF}rPwrJ",
                            "fields": {
                             "VAR": {
                              "id": "WWbfq-1I)$$#l.vtB(72"
                             }
                            }
                           }
                          }
                         }
                        }
                       }
                      },
                      "next": {
                       "block": {
                        "type": "Sc_Play",
                        "id": "@)H)KZJ9k#d}n}1Wpx(7",
                        "inputs": {
                         "CODE": {
                          "block": {
                           "type": "Sc_BinaryOp",
                           "id": "q7}X2T2!JNqCc(hquB1X",
                           "inline": true,
                           "fields": {
                            "OP": "*"
                           },
                           "inputs": {
                            "LHS": {
                             "block": {
                              "type": "Sc_Mix",
                              "id": "Rf2^M}6D}8x;9T0R|ZY5",
                              "inline": true,
                              "inputs": {
                               "INARRAY": {
                                "shadow": {
                                 "type": "math_number",
                                 "id": "OPWa,ZqX7}L+=ZG!xDW8",
                                 "fields": {
                                  "NUM": 0
                                 }
                                },
                                "block": {
                                 "type": "Sc_BinaryOp",
                                 "id": "iZ#nXvHcnHZ-AY!U`t71",
                                 "inline": true,
                                 "fields": {
                                  "OP": "*"
                                 },
                                 "inputs": {
                                  "LHS": {
                                   "block": {
                                    "type": "Sc_SinOsc",
                                    "id": "XC2?PB]%C|NVp0JqsOH$",
                                    "inline": true,
                                    "inputs": {
                                     "FREQ": {
                                      "block": {
                                       "type": "variables_get",
                                       "id": "$FOi_q^N1Cew+D8NC1sJ",
                                       "fields": {
                                        "VAR": {
                                         "id": "uTY9bqBm5*:wUjuQ(0@N"
                                        }
                                       }
                                      }
                                     },
                                     "PHASE": {
                                      "block": {
                                       "type": "math_number",
                                       "id": "SI/47957Un?:Gmn|6qr}",
                                       "fields": {
                                        "NUM": 0
                                       }
                                      }
                                     },
                                     "MUL": {
                                      "shadow": {
                                       "type": "math_number",
                                       "id": "XBft=QO3VSXd1Hq+kd40",
                                       "fields": {
                                        "NUM": 1
                                       }
                                      }
                                     },
                                     "ADD": {
                                      "shadow": {
                                       "type": "math_number",
                                       "id": "6-$]c_PwM-d{=_5[}{,9",
                                       "fields": {
                                        "NUM": 0
                                       }
                                      }
                                     }
                                    }
                                   }
                                  },
                                  "RHS": {
                                   "block": {
                                    "type": "variables_get",
                                    "id": ";=kN=8AuaC|8ZH~C*[]f",
                                    "fields": {
                                     "VAR": {
                                      "id": "ewK2$,B*9$K-@m3*cnWs"
                                     }
                                    }
                                   }
                                  }
                                 }
                                }
                               }
                              }
                             }
                            },
                            "RHS": {
                             "block": {
                              "type": "math_number",
                              "id": "2jIkv2.sq.VKSyHW^!gy",
                              "fields": {
                               "NUM": 0.01
                              }
                             }
                            }
                           }
                          }
                         }
                        }
                       }
                      }
                     }
                    }
                   }
                  }
                 }
                }
               }
              }
             }
            }
           }
          }
         }
        }
       }
      }
     }
    }
   }
  ]
 },
 "variables": [
  {
   "name": "x",
   "id": "ft8wODt6uo)_f/Dl#?(G"
  },
  {
   "name": "y",
   "id": "R$HXOP(9X.:kG=s+dhzt"
  },
  {
   "name": "i",
   "id": "xZLz3r*Z0?fDdj!]P5=["
  },
  {
   "name": "d",
   "id": "6=p[(Vi!RJ=~tGwys3XS"
  },
  {
   "name": "a",
   "id": "WWbfq-1I)$$#l.vtB(72"
  },
  {
   "name": "z1",
   "id": "UQ5_RVY~(jTNVvJ@sY#U"
  },
  {
   "name": "z2",
   "id": "x~3U?9rn;:L#]M/uSTy_"
  },
  {
   "name": "freq",
   "id": "uTY9bqBm5*:wUjuQ(0@N"
  },
  {
   "name": "c",
   "id": "ewK2$,B*9$K-@m3*cnWs"
  }
 ]
}
