<xml xmlns="https://developers.google.com/blockly/xml">
  <variables>
    <variable id="O9~14b1)`~27[p}G7iZ!">i</variable>
    <variable id="+)Ko5ez%=|V/_bWH1Mt8">c</variable>
    <variable id="HAd~%^%#Z[,mlYyObR4)">d</variable>
  </variables>
  <block type="sc3_Comment" id="r7qPzXO!nI1XPa~UtJnh" x="0" y="0">
    <field name="COMMENT">https://sccode.org/1-4Qy ; f0 ; 0297</field>
    <next>
      <block type="sc3_Play" id="30;|rn[F#/]Azx/F1Kcf">
        <value name="CODE">
          <block type="sc3_ArrayProc1" id="82E;]o2.vs)d$5`1W{c3">
            <field name="OP">sum</field>
            <value name="IN">
              <block type="sc3_ArrayProc1" id="%cWR1_=)qE=*2YzHm*Sa">
                <field name="OP">transposed</field>
                <value name="IN">
                  <block type="sc3_Splay2" id="Q^z@%Y8ICb68;5Gq$fxq" inline="false">
                    <value name="INARRAY">
                      <block type="sc3_ArrayProc2" id="{S9y=~d*`PDO{C{-`6#d" inline="false">
                        <field name="OP">collect</field>
                        <value name="LHS">
                          <block type="sc3_ArrayFromTo" id="-H5D_*)gzr-iZ_}Gv[aH" inline="true">
                            <value name="FROM">
                              <block type="math_number" id="/~g@)KPd5v)l)bmHLxoh">
                                <field name="NUM">0</field>
                              </block>
                            </value>
                            <value name="TO">
                              <block type="math_number" id="nO?KLqpLL1kFy[V{HC0E">
                                <field name="NUM">3</field>
                              </block>
                            </value>
                          </block>
                        </value>
                        <value name="RHS">
                          <block type="sc3_Proc1Stm" id="|ZJ@^s]l?1}$OmfC%QOO">
                            <value name="VAR">
                              <block type="variables_get" id="BJAx_oY2cc8M~`:#bTdq">
                                <field name="VAR" id="O9~14b1)`~27[p}G7iZ!">i</field>
                              </block>
                            </value>
                            <statement name="STATEMENTS">
                              <block type="variables_set" id="1qhE9VYu|TxYg7EY~$_Z">
                                <field name="VAR" id="+)Ko5ez%=|V/_bWH1Mt8">c</field>
                                <value name="VALUE">
                                  <block type="sc3_BinaryOp" id=",E1U.(FKW=)7F1Rd-nMs" inline="false">
                                    <field name="OP">/</field>
                                    <value name="LHS">
                                      <block type="sc3_SinOscFB" id="ECe?71zun$WpC4FH,*/$" inline="true">
                                        <value name="FREQ">
                                          <block type="sc3_BinaryOp" id="FiW2|lx*0OE)iMUt*P_#" inline="true">
                                            <field name="OP">/</field>
                                            <value name="LHS">
                                              <block type="sc3_BinaryOp" id="mSCDWAmc|%)]wmeb5a)A" inline="true">
                                                <field name="OP">+</field>
                                                <value name="LHS">
                                                  <block type="variables_get" id="{C/xph?kiZ4?0@HEF);@">
                                                    <field name="VAR" id="O9~14b1)`~27[p}G7iZ!">i</field>
                                                  </block>
                                                </value>
                                                <value name="RHS">
                                                  <block type="math_number" id="vzWgV2v!9_l((U`Qy?Q`">
                                                    <field name="NUM">1</field>
                                                  </block>
                                                </value>
                                              </block>
                                            </value>
                                            <value name="RHS">
                                              <block type="lists_create_with" id="50W$%80{~l+Oe,VGY/ef" inline="true">
                                                <mutation items="2"></mutation>
                                                <value name="ADD0">
                                                  <block type="math_number" id="Rr]o;#h*6gV^y13HaJCR">
                                                    <field name="NUM">6</field>
                                                  </block>
                                                </value>
                                                <value name="ADD1">
                                                  <block type="math_number" id=".w7rudnq,ila41OC|Vu,">
                                                    <field name="NUM">4</field>
                                                  </block>
                                                </value>
                                              </block>
                                            </value>
                                          </block>
                                        </value>
                                        <value name="FEEDBACK">
                                          <block type="math_number" id="BO,8i`Mx8tLlKnm=+qw(">
                                            <field name="NUM">0</field>
                                          </block>
                                        </value>
                                        <value name="MUL">
                                          <shadow type="math_number" id="5R?uM_.~!yDsZJdx|c)=">
                                            <field name="NUM">1</field>
                                          </shadow>
                                        </value>
                                        <value name="ADD">
                                          <shadow type="math_number" id="zLX,9|Jv5T+V}~*T%%U5">
                                            <field name="NUM">0</field>
                                          </shadow>
                                        </value>
                                      </block>
                                    </value>
                                    <value name="RHS">
                                      <block type="sc3_SinOscFB" id="wI^D#g*8~jMaQwHWcQG{" inline="true">
                                        <value name="FREQ">
                                          <block type="sc3_BinaryOp" id="{I~bP~,]Y}bKtfH{0z.^" inline="true">
                                            <field name="OP">/</field>
                                            <value name="LHS">
                                              <block type="math_number" id="4`u2N~*Ejih$j!pgk=mq">
                                                <field name="NUM">1</field>
                                              </block>
                                            </value>
                                            <value name="RHS">
                                              <block type="lists_create_with" id=".c)GNk8{Ck;7`fm69m8V" inline="true">
                                                <mutation items="2"></mutation>
                                                <value name="ADD0">
                                                  <block type="math_number" id="y9bt2)0LmX!tHvi+yTSI">
                                                    <field name="NUM">8</field>
                                                  </block>
                                                </value>
                                                <value name="ADD1">
                                                  <block type="math_number" id="+VJenCx?~moq36C_Rg+S">
                                                    <field name="NUM">9</field>
                                                  </block>
                                                </value>
                                              </block>
                                            </value>
                                          </block>
                                        </value>
                                        <value name="FEEDBACK">
                                          <block type="math_number" id="-3_$T0LWq|O+F7]{ZrY9">
                                            <field name="NUM">0</field>
                                          </block>
                                        </value>
                                        <value name="MUL">
                                          <shadow type="math_number" id="5f#%xx/qU8/y.Y}JPZW?">
                                            <field name="NUM">1</field>
                                          </shadow>
                                        </value>
                                        <value name="ADD">
                                          <shadow type="math_number" id=";[w*lRIJ;H(z+}bgZB8c">
                                            <field name="NUM">0</field>
                                          </shadow>
                                          <block type="math_number" id=":/pbhX`Jsiw(nYuN#=if">
                                            <field name="NUM">1.5</field>
                                          </block>
                                        </value>
                                      </block>
                                    </value>
                                  </block>
                                </value>
                                <next>
                                  <block type="variables_set" id="iPK_(Sy1AsMI8Td@PYl6">
                                    <field name="VAR" id="HAd~%^%#Z[,mlYyObR4)">d</field>
                                    <value name="VALUE">
                                      <block type="sc3_BinaryOp" id=",TzKf%]K:QA_nUx+{iyG" inline="true">
                                        <field name="OP">%</field>
                                        <value name="LHS">
                                          <block type="variables_get" id="MvWN(VD$jp%HaY25P,w(">
                                            <field name="VAR" id="+)Ko5ez%=|V/_bWH1Mt8">c</field>
                                          </block>
                                        </value>
                                        <value name="RHS">
                                          <block type="sc3_DelayN" id="iWC6Y+iyE}`l4hg81rLj" inline="true">
                                            <value name="IN">
                                              <block type="variables_get" id=").^%A=(bOAQYC,w4gTnX">
                                                <field name="VAR" id="+)Ko5ez%=|V/_bWH1Mt8">c</field>
                                              </block>
                                            </value>
                                            <value name="MAXDELAYTIME">
                                              <block type="math_number" id="Qk%;J_8/516r{a$Wtn2?">
                                                <field name="NUM">0.2</field>
                                              </block>
                                            </value>
                                            <value name="DELAYTIME">
                                              <block type="math_number" id="N}Y::;Sju7..KoLf:ydm">
                                                <field name="NUM">0.2</field>
                                              </block>
                                            </value>
                                            <value name="MUL">
                                              <shadow type="math_number" id="^])aq:hR7BU*V$*[R/b?">
                                                <field name="NUM">1</field>
                                              </shadow>
                                            </value>
                                            <value name="ADD">
                                              <shadow type="math_number" id="`mGHT1ow1=Y,9hFi3cJC">
                                                <field name="NUM">0</field>
                                              </shadow>
                                            </value>
                                          </block>
                                        </value>
                                      </block>
                                    </value>
                                  </block>
                                </next>
                              </block>
                            </statement>
                            <value name="RETURN">
                              <block type="sc3_BinaryOp" id="RsWc=g}^z(pqr#nUY3?z" inline="false">
                                <field name="OP">*</field>
                                <value name="LHS">
                                  <block type="sc3_SinOscFB" id="P%y3S:X25sXuFO*2CXHK" inline="true">
                                    <value name="FREQ">
                                      <block type="sc3_BinaryOp" id="fB:+6Z%I10q2/L4K9~+6" inline="true">
                                        <field name="OP">*</field>
                                        <value name="LHS">
                                          <block type="sc3_BinaryOp" id="!U{a%s0MyNm17:$mz3Fn" inline="true">
                                            <field name="OP">+</field>
                                            <value name="LHS">
                                              <block type="sc3_BinaryOp" id="qkso_:./i*:!,S}zJS,I" inline="true">
                                                <field name="OP">**</field>
                                                <value name="LHS">
                                                  <block type="sc3_BinaryOp" id="I`+Vlk3]hL9[vyI#S5:D" inline="true">
                                                    <field name="OP">+</field>
                                                    <value name="LHS">
                                                      <block type="math_number" id=",^KK|M@9q(AP.lsXhYlg">
                                                        <field name="NUM">1</field>
                                                      </block>
                                                    </value>
                                                    <value name="RHS">
                                                      <block type="variables_get" id=";@r:@[uLQxg`ra;{Ct]m">
                                                        <field name="VAR" id="+)Ko5ez%=|V/_bWH1Mt8">c</field>
                                                      </block>
                                                    </value>
                                                  </block>
                                                </value>
                                                <value name="RHS">
                                                  <block type="variables_get" id="2LZHK]J2f[Gds2P]7bp8">
                                                    <field name="VAR" id="O9~14b1)`~27[p}G7iZ!">i</field>
                                                  </block>
                                                </value>
                                              </block>
                                            </value>
                                            <value name="RHS">
                                              <block type="variables_get" id="AlXuyD%^|m[,4r?Fyu$^">
                                                <field name="VAR" id="O9~14b1)`~27[p}G7iZ!">i</field>
                                              </block>
                                            </value>
                                          </block>
                                        </value>
                                        <value name="RHS">
                                          <block type="math_number" id=",+JKGgjPq!8bh}s^w~nb">
                                            <field name="NUM">99</field>
                                          </block>
                                        </value>
                                      </block>
                                    </value>
                                    <value name="FEEDBACK">
                                      <block type="variables_get" id="C]*drMXc/O@0n61afPb:">
                                        <field name="VAR" id="HAd~%^%#Z[,mlYyObR4)">d</field>
                                      </block>
                                    </value>
                                    <value name="MUL">
                                      <shadow type="math_number" id="}fvo5zt_xK`Nh3r/xaHe">
                                        <field name="NUM">1</field>
                                      </shadow>
                                    </value>
                                    <value name="ADD">
                                      <shadow type="math_number" id="Hn_c?-:,XD{{,2]:g~*!">
                                        <field name="NUM">0</field>
                                      </shadow>
                                    </value>
                                  </block>
                                </value>
                                <value name="RHS">
                                  <block type="sc3_Lag3" id="Rq{qMOBh$IC?QE*/j2XJ" inline="true">
                                    <value name="IN">
                                      <block type="variables_get" id="I*cBFl:oc;(wBlJIaKl8">
                                        <field name="VAR" id="HAd~%^%#Z[,mlYyObR4)">d</field>
                                      </block>
                                    </value>
                                    <value name="LAGTIME">
                                      <block type="sc3_BinaryOp" id="F*nx[-z1S)$9amRNc,,." inline="true">
                                        <field name="OP">/</field>
                                        <value name="LHS">
                                          <block type="sc3_BinaryOp" id="#)Knv`j-5Ee}:_Sz8%;/" inline="true">
                                            <field name="OP">%</field>
                                            <value name="LHS">
                                              <block type="variables_get" id="[%gk)b?ZH_K/3{vkH1SC">
                                                <field name="VAR" id="+)Ko5ez%=|V/_bWH1Mt8">c</field>
                                              </block>
                                            </value>
                                            <value name="RHS">
                                              <block type="math_number" id="6Y(vaaF!D2AqQBruFeGQ">
                                                <field name="NUM">1</field>
                                              </block>
                                            </value>
                                          </block>
                                        </value>
                                        <value name="RHS">
                                          <block type="math_number" id="s9:F33xTCHq35:4a@u~*">
                                            <field name="NUM">99</field>
                                          </block>
                                        </value>
                                      </block>
                                    </value>
                                    <value name="MUL">
                                      <shadow type="math_number" id="8G+ys^jY`4vZ|Y:%09l$">
                                        <field name="NUM">1</field>
                                      </shadow>
                                    </value>
                                    <value name="ADD">
                                      <shadow type="math_number" id="XbnyMtQ_#:_g)4-8r!Q_">
                                        <field name="NUM">0</field>
                                      </shadow>
                                    </value>
                                  </block>
                                </value>
                              </block>
                            </value>
                          </block>
                        </value>
                      </block>
                    </value>
                    <value name="MUL">
                      <block type="sc3_BinaryOp" id="$zY7HdXhivas+vjBAcj3" inline="true">
                        <field name="OP">/</field>
                        <value name="LHS">
                          <block type="math_number" id="~s~XiTKriUkUlKtOI_.c">
                            <field name="NUM">1</field>
                          </block>
                        </value>
                        <value name="RHS">
                          <block type="math_number" id="h.xw(*C.H!Zj{tPxnv]w">
                            <field name="NUM">3</field>
                          </block>
                        </value>
                      </block>
                    </value>
                    <value name="ADD">
                      <block type="math_number" id=":5L|4GG5xM|g8by}cU@n">
                        <field name="NUM">0</field>
                      </block>
                    </value>
                  </block>
                </value>
              </block>
            </value>
          </block>
        </value>
      </block>
    </next>
  </block>
</xml>
