<xml xmlns="https://developers.google.com/blockly/xml">
  <variables>
    <variable id=";~wLL[G#K%wbQ}W`dxh2">tr</variable>
    <variable id="pjvjd86kQ)s[4wIe:K:i">gt</variable>
  </variables>
  <block type="sc3_Comment" id="[TN`RFHzHeY-]L*oqM`Q" x="0" y="0">
    <field name="COMMENT">Adsr</field>
    <next>
      <block type="variables_set" id="*(%0J:fzRk%$;dbdrLNH">
        <field name="VAR" id=";~wLL[G#K%wbQ}W`dxh2">tr</field>
        <value name="VALUE">
          <block type="sc3_Impulse" id="37Ov+,H#MazKAVyUI5WH" inline="true">
            <value name="FREQ">
              <block type="lists_create_with" id="DOe.{j(Z.JJmv1wC]d4_" inline="true">
                <mutation items="2"></mutation>
                <value name="ADD0">
                  <block type="math_number" id="}y}^a!Y0LjvjpBj#Kbn:">
                    <field name="NUM">0.75</field>
                  </block>
                </value>
                <value name="ADD1">
                  <block type="math_number" id="KcH^](ClHjsstK;CRq|i">
                    <field name="NUM">0.5</field>
                  </block>
                </value>
              </block>
            </value>
            <value name="PHASE">
              <block type="math_number" id="dYF{n[3W{6O$?m;TA}F8">
                <field name="NUM">0</field>
              </block>
            </value>
            <value name="MUL">
              <shadow type="math_number" id="yv9YXwQ~OufImH2EPVUx">
                <field name="NUM">1</field>
              </shadow>
            </value>
            <value name="ADD">
              <shadow type="math_number" id="A*[85/$c7`G,YYjW!gz:">
                <field name="NUM">0</field>
              </shadow>
            </value>
          </block>
        </value>
        <next>
          <block type="variables_set" id="ia=da6eRyxy0]g/sW8F?">
            <field name="VAR" id="pjvjd86kQ)s[4wIe:K:i">gt</field>
            <value name="VALUE">
              <block type="sc3_Trig" id="NS1?YyooWtW}?wVF%rWg" inline="true">
                <value name="IN">
                  <block type="variables_get" id="WGf3fi]zl8#e4MWO~a_|">
                    <field name="VAR" id=";~wLL[G#K%wbQ}W`dxh2">tr</field>
                  </block>
                </value>
                <value name="DUR">
                  <block type="sc3_TRand" id="1@92elo3:oR@=9-OIwS^" inline="true">
                    <value name="LO">
                      <block type="math_number" id="jo8-pM`(oRy0my/4Fx%a">
                        <field name="NUM">0.1</field>
                      </block>
                    </value>
                    <value name="HI">
                      <block type="math_number" id=",N]7eUpq8r6FdT=ahd9i">
                        <field name="NUM">0.2</field>
                      </block>
                    </value>
                    <value name="TRIG">
                      <block type="variables_get" id="yf3_@Q~Q@}gb~(9ZVY/2">
                        <field name="VAR" id=";~wLL[G#K%wbQ}W`dxh2">tr</field>
                      </block>
                    </value>
                    <value name="MUL">
                      <shadow type="math_number" id="!Jr[rB3pXt0xdJ#~iL6[">
                        <field name="NUM">1</field>
                      </shadow>
                    </value>
                    <value name="ADD">
                      <shadow type="math_number" id="d)s~Ff1OkG~H[q9F9KcE">
                        <field name="NUM">0</field>
                      </shadow>
                    </value>
                  </block>
                </value>
                <value name="MUL">
                  <shadow type="math_number" id="h~Redm}vmL^%SH2}P4i@">
                    <field name="NUM">1</field>
                  </shadow>
                </value>
                <value name="ADD">
                  <shadow type="math_number" id="%[942G8/}S(NMfyrsP%b">
                    <field name="NUM">0</field>
                  </shadow>
                </value>
              </block>
            </value>
            <next>
              <block type="sc3_Play" id="#)AhBm.~K:$33|,5VyOF">
                <value name="CODE">
                  <block type="sc3_Blip" id="a3Ic/JVQl6:OhreT,v31" inline="false">
                    <value name="FREQ">
                      <block type="sc3_UnaryOp" id="nT]A2YmOvfmaF+N344]7">
                        <field name="OP">midiCps</field>
                        <value name="IN">
                          <block type="sc3_TRand" id="r%iSM44Q_);uk$=aFl,Y" inline="true">
                            <value name="LO">
                              <block type="math_number" id="-FRgc})#WM)11@Jsl|$I">
                                <field name="NUM">36</field>
                              </block>
                            </value>
                            <value name="HI">
                              <block type="lists_create_with" id="y*Jq#QRR7d?NleCa!imP" inline="true">
                                <mutation items="2"></mutation>
                                <value name="ADD0">
                                  <block type="math_number" id="Ey5CKyT$wqSL)!c`gwZD">
                                    <field name="NUM">48</field>
                                  </block>
                                </value>
                                <value name="ADD1">
                                  <block type="math_number" id="i0`uF41XxdP+W?(WJ)@U">
                                    <field name="NUM">72</field>
                                  </block>
                                </value>
                              </block>
                            </value>
                            <value name="TRIG">
                              <block type="variables_get" id="G,W=#gVU(;8_{JW/=mwo">
                                <field name="VAR" id=";~wLL[G#K%wbQ}W`dxh2">tr</field>
                              </block>
                            </value>
                            <value name="MUL">
                              <shadow type="math_number" id="I;(5b=L;K$.!NyfP.n_V">
                                <field name="NUM">1</field>
                              </shadow>
                            </value>
                            <value name="ADD">
                              <shadow type="math_number" id="1rIFQDPocjI%bH^v~];{">
                                <field name="NUM">0</field>
                              </shadow>
                            </value>
                          </block>
                        </value>
                      </block>
                    </value>
                    <value name="NUMHARM">
                      <block type="sc3_TRand" id="@8{DQli-z9lhFf{sm9:F" inline="true">
                        <value name="LO">
                          <block type="math_number" id="~?0q%ie{e]sB?i2j@v.4">
                            <field name="NUM">1</field>
                          </block>
                        </value>
                        <value name="HI">
                          <block type="math_number" id="|Nfhz#Pj[7f2gL)5,[w0">
                            <field name="NUM">7</field>
                          </block>
                        </value>
                        <value name="TRIG">
                          <block type="variables_get" id="9VUbc(FcBdpFx6RI?U7;">
                            <field name="VAR" id=";~wLL[G#K%wbQ}W`dxh2">tr</field>
                          </block>
                        </value>
                        <value name="MUL">
                          <shadow type="math_number" id="U1*gW9s(FW[@(?92W}d2">
                            <field name="NUM">1</field>
                          </shadow>
                        </value>
                        <value name="ADD">
                          <shadow type="math_number" id="%s=r4pUCK9#E4Ikr1s/z">
                            <field name="NUM">0</field>
                          </shadow>
                        </value>
                      </block>
                    </value>
                    <value name="MUL">
                      <shadow type="math_number" id="5L1p2U-{?O7(bW*_31eb">
                        <field name="NUM">1</field>
                      </shadow>
                      <block type="sc3_Adsr" id="BwYxSH}/A;6YPm=.WmYt" inline="false">
                        <value name="GATE">
                          <block type="variables_get" id="mNo7~A*_b?(gN$39?sGF">
                            <field name="VAR" id="pjvjd86kQ)s[4wIe:K:i">gt</field>
                          </block>
                        </value>
                        <value name="ATTACKTIME">
                          <block type="sc3_TRand" id="/{$rXB.7^1+*Q0cD@W6Y" inline="true">
                            <value name="LO">
                              <block type="math_number" id="?hv_r^8c|r^}SfV/npq+">
                                <field name="NUM">0.01</field>
                              </block>
                            </value>
                            <value name="HI">
                              <block type="math_number" id="v`@dO]P!cc--84ID(=5r">
                                <field name="NUM">0.2</field>
                              </block>
                            </value>
                            <value name="TRIG">
                              <block type="variables_get" id="8Q!92Qhl[lKf!}l840En">
                                <field name="VAR" id=";~wLL[G#K%wbQ}W`dxh2">tr</field>
                              </block>
                            </value>
                            <value name="MUL">
                              <shadow type="math_number" id="`cQO`W-H5r(5#f][,PoR">
                                <field name="NUM">1</field>
                              </shadow>
                            </value>
                            <value name="ADD">
                              <shadow type="math_number" id="IC^qXR{cKjDZZ^wFyeg?">
                                <field name="NUM">0</field>
                              </shadow>
                            </value>
                          </block>
                        </value>
                        <value name="DECAYTIME">
                          <block type="sc3_TRand" id="!:dg^EaE)G4^(9x$O1I]" inline="true">
                            <value name="LO">
                              <block type="math_number" id="FMn7*@Cg{|Ua7k5H4#r#">
                                <field name="NUM">0.3</field>
                              </block>
                            </value>
                            <value name="HI">
                              <block type="math_number" id="$1NFR6=*?[soy(N)ttgr">
                                <field name="NUM">0.6</field>
                              </block>
                            </value>
                            <value name="TRIG">
                              <block type="variables_get" id="_.pA)x_d/C9#2oet2Snd">
                                <field name="VAR" id=";~wLL[G#K%wbQ}W`dxh2">tr</field>
                              </block>
                            </value>
                            <value name="MUL">
                              <shadow type="math_number" id="5J}G,Z{2.wg+k^:PNrE=">
                                <field name="NUM">1</field>
                              </shadow>
                            </value>
                            <value name="ADD">
                              <shadow type="math_number" id="@n`V{3Y$eiT!fMan!Ry:">
                                <field name="NUM">0</field>
                              </shadow>
                            </value>
                          </block>
                        </value>
                        <value name="SUSTAINLEVEL">
                          <block type="sc3_TRand" id="2%nDFb[|i-z]b;f(gX5]" inline="true">
                            <value name="LO">
                              <block type="math_number" id="d%5=Zl;W=Id]3s{xX|M7">
                                <field name="NUM">0.4</field>
                              </block>
                            </value>
                            <value name="HI">
                              <block type="math_number" id="TthID;W,:mY|jMEvg$6[">
                                <field name="NUM">0.6</field>
                              </block>
                            </value>
                            <value name="TRIG">
                              <block type="variables_get" id="hEL^g9jiOXrK5%s0X/0D">
                                <field name="VAR" id=";~wLL[G#K%wbQ}W`dxh2">tr</field>
                              </block>
                            </value>
                            <value name="MUL">
                              <shadow type="math_number" id="js`E?nD5FUK/+Suzvf`Q">
                                <field name="NUM">1</field>
                              </shadow>
                            </value>
                            <value name="ADD">
                              <shadow type="math_number" id="QK9YD;NWPq=!Pc9a:t=1">
                                <field name="NUM">0</field>
                              </shadow>
                            </value>
                          </block>
                        </value>
                        <value name="RELEASETIME">
                          <block type="sc3_TRand" id="Mhd7GknR{MMIm.7p04u}" inline="true">
                            <value name="LO">
                              <block type="math_number" id=".~YUVu~^Tjgwcf(U(.vI">
                                <field name="NUM">0.5</field>
                              </block>
                            </value>
                            <value name="HI">
                              <block type="math_number" id="5=G7zp=DucXV~r6)q#PU">
                                <field name="NUM">2</field>
                              </block>
                            </value>
                            <value name="TRIG">
                              <block type="variables_get" id="1~JK)yt!|]Bw~LlzVlXe">
                                <field name="VAR" id=";~wLL[G#K%wbQ}W`dxh2">tr</field>
                              </block>
                            </value>
                            <value name="MUL">
                              <shadow type="math_number" id="rVI0(Y*[$Hd1G:g|;1mV">
                                <field name="NUM">1</field>
                              </shadow>
                            </value>
                            <value name="ADD">
                              <shadow type="math_number" id=",KXXM8*vqs%?1u`#6sj6">
                                <field name="NUM">0</field>
                              </shadow>
                            </value>
                          </block>
                        </value>
                        <value name="CURVES">
                          <block type="math_number" id="lL?2V]+/U*mri.hShFHZ">
                            <field name="NUM">-4</field>
                          </block>
                        </value>
                        <value name="MUL">
                          <shadow type="math_number" id="jg4$Ia714hmJ}Y:CTcRq">
                            <field name="NUM">1</field>
                          </shadow>
                          <block type="math_number" id="L?pQx43WkPkLwTD9-}Z;">
                            <field name="NUM">0.1</field>
                          </block>
                        </value>
                        <value name="ADD">
                          <shadow type="math_number" id="S*BQ4}^|AZ,ny26N1Yka">
                            <field name="NUM">0</field>
                          </shadow>
                        </value>
                      </block>
                    </value>
                    <value name="ADD">
                      <shadow type="math_number" id="54CqUW-ui5x$QqMurO?d">
                        <field name="NUM">0</field>
                      </shadow>
                    </value>
                  </block>
                </value>
              </block>
            </next>
          </block>
        </next>
      </block>
    </next>
  </block>
</xml>
